qbt/__init__.py
qbt/cli.py
qbt/config.py
qbt/core/broker.py
qbt/core/engine.py
qbt/core/engine_multi.py
qbt/core/metrics.py
qbt/core/portfolio.py
qbt/core/portfolio_multi.py
qbt/core/visualize.py
qbt/data/loader.py
qbt/report/report.py
qbt/strategies/base.py
qbt/strategies/momentum.py
qbt/strategies/sma_cross.py
qbt/strategies/ta_bbands.py
qbt/strategies/ta_macd.py
qbt/strategies/ta_rsi.py
qbt/strategies/topn_momentum.py
qbt_lite-0.3.0.dist-info/METADATA
qbt_lite-0.3.0.dist-info/WHEEL
qbt_lite-0.3.0.dist-info/entry_points.txt
qbt_lite-0.3.0.dist-info/top_level.txt
qbt_lite-0.3.0.dist-info/RECORD
