Metadata-Version: 2.4
Name: qbt-lite
Version: 0.3.0
Summary: A lightweight quantitative backtesting framework with CLI, strategies, reporting, and Streamlit dashboard.
Author-email: Su Li <princesslsy2003@gmail.com>
License: MIT
Keywords: quantitative-finance,backtesting,trading,pandas,streamlit,momentum
Classifier: Programming Language :: Python :: 3
Classifier: License :: OSI Approved :: MIT License
Classifier: Operating System :: OS Independent
Requires-Python: >=3.9
Requires-Dist: pandas>=1.5
Requires-Dist: numpy>=1.22
Requires-Dist: matplotlib>=3.6
Requires-Dist: pyyaml>=6.0
Requires-Dist: tabulate>=0.9
Provides-Extra: interactive
Requires-Dist: streamlit>=1.28; extra == "interactive"
Requires-Dist: plotly>=5.18; extra == "interactive"
Requires-Dist: yfinance>=0.2; extra == "interactive"
Provides-Extra: dev
Requires-Dist: pytest>=7.0; extra == "dev"
Requires-Dist: build>=1.0.0; extra == "dev"
Requires-Dist: twine>=5.0.0; extra == "dev"
